aws_ac-0.0.4.dist-info/DESCRIPTION.rst
aws_ac-0.0.4.dist-info/METADATA
aws_ac-0.0.4.dist-info/RECORD
aws_ac-0.0.4.dist-info/WHEEL
aws_ac-0.0.4.dist-info/entry_points.txt
aws_ac-0.0.4.dist-info/metadata.json
aws_ac-0.0.4.dist-info/top_level.txt
awsac/__init__.py
awsac/__version__.py
awsac/cli.py
awsac/core.py
