Metadata-Version: 2.0
Name: aws-ac
Version: 0.0.4
Summary: Auto Configure aws-cli & ecs-cli
Home-page: https://github.com/djstein/aws-ac
Author: Dylan Stein
Author-email: djstein@ncsu.edu
License: UNKNOWN
Platform: UNKNOWN
Classifier: Programming Language :: Python
Classifier: Programming Language :: Python :: 3.6
Classifier: Programming Language :: Python :: Implementation :: CPython
Classifier: Programming Language :: Python :: Implementation :: PyPy
Requires-Dist: click
Requires-Dist: requests
